{
  "timestamp": "2025-10-20T01:22:31+09:00",
  "issues": [
    {
      "severity": "critical",
      "type": "Hardcoded PGP Private Key",
      "file": "scripts/security_check.py",
      "line": 40,
      "message": "PGP Private Key \u304c\u691c\u51fa\u3055\u308c\u307e\u3057\u305f",
      "code": "(r'-----BEGIN PGP PRIVATE KEY BLOCK-----', 'PGP Private Key'),"
    },
    {
      "severity": "warning",
      "type": "Insecure HTTP",
      "file": "scripts/security_check.py",
      "line": 190,
      "message": "Insecure HTTP \u306e\u53ef\u80fd\u6027\u304c\u3042\u308a\u307e\u3059",
      "code": "(r'http://(?!localhost|127\\.0\\.0\\.1)', 'Insecure HTTP', 'warning'),"
    }
  ],
  "summary": {
    "total": 2,
    "critical": 1,
    "high": 0,
    "warning": 1
  },
  "passed": false
}